atmoswing_vigicrues/__init__.py
atmoswing_vigicrues/__main__.py
atmoswing_vigicrues/controller.py
atmoswing_vigicrues/exceptions.py
atmoswing_vigicrues/options.py
atmoswing_vigicrues/utils.py
atmoswing_vigicrues/disseminations/__init__.py
atmoswing_vigicrues/disseminations/dissemination.py
atmoswing_vigicrues/disseminations/transfer_ftp_out.py
atmoswing_vigicrues/disseminations/transfer_sftp_out.py
atmoswing_vigicrues/postactions/__init__.py
atmoswing_vigicrues/postactions/export_bdapbp.py
atmoswing_vigicrues/postactions/export_prv.py
atmoswing_vigicrues/postactions/postaction.py
atmoswing_vigicrues/preactions/__init__.py
atmoswing_vigicrues/preactions/download_gfs.py
atmoswing_vigicrues/preactions/preaction.py
atmoswing_vigicrues/preactions/transfer_sftp_in.py
atmoswing_vigicrues/preactions/transform_ecmwf.py
atmoswing_vigicrues/preactions/transform_gfs.py
atmoswing_vigicrues-1.2.0.dist-info/licenses/LICENSE
atmoswing_vigicrues-1.2.0.dist-info/METADATA
atmoswing_vigicrues-1.2.0.dist-info/WHEEL
atmoswing_vigicrues-1.2.0.dist-info/top_level.txt
atmoswing_vigicrues-1.2.0.dist-info/RECORD
