Metadata-Version: 2.4
Name: atmoswing-vigicrues
Version: 1.2.0
Summary: Package to integrate AtmoSwing in the Vigicrues network.
Author: Pascal Horton
Author-email: Pascal Horton <pascal.horton@terranum.ch>
Classifier: Programming Language :: Python :: 3
Classifier: License :: OSI Approved :: MIT License
Classifier: Operating System :: OS Independent
Requires-Python: >=3.7
License-File: LICENSE
Dynamic: author
Dynamic: license-file
